quri_parts/tensornetwork/NOTICE
quri_parts/tensornetwork/__init__.py
quri_parts/tensornetwork/circuit/__init__.py
quri_parts/tensornetwork/circuit/gates.py
quri_parts/tensornetwork/estimator.py
quri_parts/tensornetwork/operator/__init__.py
quri_parts/tensornetwork/py.typed
quri_parts/tensornetwork/sampler.py
quri_parts/tensornetwork/state/__init__.py
quri_parts_tensornetwork-0.24.1.dist-info/LICENSE
quri_parts_tensornetwork-0.24.1.dist-info/METADATA
quri_parts_tensornetwork-0.24.1.dist-info/WHEEL
quri_parts_tensornetwork-0.24.1.dist-info/RECORD
